dbt/adapters/flink/__init__.py
dbt/adapters/flink/__version__.py
dbt/adapters/flink/connections.py
dbt/adapters/flink/handler.py
dbt/adapters/flink/impl.py
dbt/adapters/flink/query_hints_parser.py
dbt/adapters/flink/relation.py
dbt/include/flink/__init__.py
dbt/include/flink/dbt_project.yml
dbt/include/flink/profile_template.yml
dbt/include/flink/macros/adapters.sql
dbt/include/flink/macros/catalog.sql
dbt/include/flink/macros/materializations/models/create_table_as.sql
dbt/include/flink/macros/materializations/models/create_view_as.sql
dbt/include/flink/macros/materializations/seeds/helpers.sql
dbt/include/flink/macros/materializations/seeds/seed.sql
dbt/include/flink/macros/materializations/sources/source.sql
dbt/include/flink/macros/materializations/tests/helpers.sql
flink/__init__.py
flink/sqlgateway/__init__.py
flink/sqlgateway/client.py
flink/sqlgateway/config.py
flink/sqlgateway/operation.py
flink/sqlgateway/result_parser.py
flink/sqlgateway/session.py
dbt_flink_adapter-1.3.4.dist-info/LICENSE
dbt_flink_adapter-1.3.4.dist-info/METADATA
dbt_flink_adapter-1.3.4.dist-info/WHEEL
dbt_flink_adapter-1.3.4.dist-info/top_level.txt
dbt_flink_adapter-1.3.4.dist-info/RECORD
