Metadata-Version: 2.1
Name: dbt-flink-adapter
Version: 1.3.4
Summary: The Flink adapter plugin for dbt
Home-page: https://github.com/getindata/flink-dbt-adapter
Author: GetInData
Author-email: office@getindata.com
Classifier: Development Status :: 5 - Production/Stable
Classifier: License :: OSI Approved :: Apache Software License
Classifier: Operating System :: Microsoft :: Windows
Classifier: Operating System :: MacOS :: MacOS X
Classifier: Operating System :: POSIX :: Linux
Classifier: Programming Language :: Python :: 3.7
Classifier: Programming Language :: Python :: 3.8
Classifier: Programming Language :: Python :: 3.9
Classifier: Programming Language :: Python :: 3.10
Requires-Python: >=3.7
License-File: LICENSE
Requires-Dist: dbt-core (~=1.3.0)
Requires-Dist: requests (<3.0.0)
